Workbook

Sheet Start Here
B2: Dance Lead Machine™
B3: Lead Tracker & Executive Dashboard — v1 Prototype
B5: How this workbook works
B6: This is the first working piece of Dance Lead Machine™: a smart lead tracker that scores every lead automatically and an Executive Dashboard that tells you who to contact first and how much money is sitting in your pipeline.
B8: 1. Log every lead on the "Leads" tab
B9: Every time someone reaches out — Instagram DM, form, QR code, walk-in, phone call — add one row. Fill in the blue cells (name, contact info, interest, source, stage, follow-up date, revenue estimate, engagement score). Everything else calculates itself.
B11: 2. Let the sheet score the lead for you
B12: The "Lead Temperature" column automatically marks each lead Hot, Warm, or Cold based on how interested they seem, what stage they're at, and how long it's been since you last talked. The "AI Next Action" column tells you exactly what to do next.
B14: 3. Check the "Dashboard" tab every morning
B15: This is your Executive Dashboard: Hot/Warm/Cold counts, follow-ups due today, pipeline value, projected revenue, close rate, business health, and an AI Coach box telling you which 2 leads to contact first and why.
B17: 4. Check the "Reference" tab if you want to customize
B18: This tab holds the dropdown lists (pipeline stages, lead sources, dance interests, instructors) and the stage-to-probability weights used to project revenue. Edit it to match your business.
... B21: This spreadsheet is the prototype. The long-term vision is for Dance Lead Machine™ to do this work automatically — an AI Receptionist that responds to inquiries, auto-books appointments, and sends follow-ups on its own. This workbook proves out the logic (scoring, coaching, dashboarding) that the automated product will eventually run in the background.

Sheet Dashboard
B2: Dance Lead Machine™ — Executive Dashboard
B3: ="Good morning! Here is where your business stands as of "&TEXT(TODAY(),"dddd, mmmm d, yyyy") -> Good morning! Here is where your business stands as of Saturday, August 8, 2026
I4: Temperature | J4: Count
B5: 🔥 HOT LEADS | C5: ☀️ WARM LEADS | D5: ❄️ COLD LEADS | E5: 📅 DUE TODAY | F5: ⚠️ OVERDUE | I5: Hot | J5: =COUNTIF(Leads!$R$2:$R$101,"Hot") -> 4
B6: =COUNTIF(Leads!R2:R101,"Hot") -> 4 | C6: =COUNTIF(Leads!R2:R101,"Warm") -> 2 | D6: =COUNTIF(Leads!R2:R101,"Cold") -> 2 | E6: =COUNTIF(Leads!Q2:Q101,"Due Today") -> 3 | F6: =COUNTIF(Leads!Q2:Q101,"Overdue") -> 2 | I6: Warm | J6: =COUNTIF(Leads!$R$2:$R$101,"Warm") -> 2
I7: Cold | J7: =COUNTIF(Leads!$R$2:$R$101,"Cold") -> 2
B8: PIPELINE VALUE (open leads) | C8: PROJECTED REVENUE (weighted) | D8: CLOSE RATE | E8: NEW LEADS (last 7 days) | F8: BUSINESS HEALTH
B9: =SUMIFS(Leads!N2:N101,Leads!I2:I101,"<>Enrolled",Leads!I2:I101,"<>Lost") -> 4980 | C9: =SUMPRODUCT(Leads!N2:N101,Leads!S2:S101) -> 3100 | D9: =IFERROR(COUNTIF(Leads!I2:I101,"Enrolled")/COUNTIFS(Leads!I2:I101,"<>New Inquiry",Leads!C2:C101,"<>"),0) -> 0.125 | E9: =COUNTIFS(Leads!B2:B101,">="&(TODAY()-7)) -> 5 | F9: =IF(COUNTIF(Leads!C2:C101,"<>")=0,"No Data",IF(AND(COUNTIF(Leads!Q2:Q101,"Overdue")=0,COUNTIF(Leads!R2:R101,"Hot")>=3),"Excellent",IF(AND(COUNTIF(Leads!Q2:Q101,"Overdue")<=2,COUNTIF(Leads!R2:R101,"Hot")>=1),"Good",IF(COUNTIF(Leads!Q2:Q101,"Overdue")>3,"Needs Attention","Fair")))) -> Good | I9: Stage | J9: Count
I10: New Inquiry | J10: =COUNTIF(Leads!$I$2:$I$101,"New Inquiry") -> 2
I11: Contacted | J11: =COUNTIF(Leads!$I$2:$I$101,"Contacted") -> 2
B12: 🤖 AI SALES COACH | I12: Qualified | J12: =COUNTIF(Leads!$I$2:$I$101,"Qualified") -> 2
B13: =IF(COUNTIF(Leads!R2:R101,"Hot")=0,"No hot leads right now. Focus on moving your Warm leads forward with a personal follow-up today.",IF(COUNTIF(Leads!R2:R101,"Hot")=1,"You have 1 Hot Lead: "&INDEX(Leads!C2:C101,MATCH(LARGE(Leads!U2:U101,1),Leads!U2:U101,0))&" — worth about "&TEXT(INDEX(Leads!N2:N101,MATCH(LARGE(Leads!U2:U101,1),Leads!U2:U101,0)),"$#,##0")&". Contact them first today.","You have "&COUNTIF(Leads!R2:R101,"Hot")&" Hot Leads. Contact these 2 first — they represent your highest revenue opportunity today:"&CHAR(10)&"1. "&INDEX(Leads!C2:C101,MATCH(LARGE(Leads!U2:U101,1),Leads!U2:U101,0))&" ("&TEXT(INDEX(Leads!N2:N101,MATCH(LARGE(Leads!U2:U101,1),Leads!U2:U101,0)),"$#,##0")&") — "&INDEX(Leads!T2:T101,MATCH(LARGE(Leads!U2:U101,1),Leads!U2:U101,0))&CHAR(10)&"2. "&INDEX(Leads!C2:C101,MATCH(LARGE(Leads!U2:U101,2),Leads!U2:U101,0))&" ("&TEXT(INDEX(Leads!N2:N101,MATCH(LARGE(Leads!U2:U101,2),Leads!U2:U101,0)),"$#,##0")&") — "&INDEX(Leads!T2:T101,MATCH(LARGE(Leads!U2:U101,2),Leads!U2:U101,0))&CHAR(10)&CHAR(10)&"Together they represent "&TEXT(INDEX(Leads!N2:N101,MATCH(LARGE(Leads!U2:U101,1),Leads!U2:U101,0))+INDEX(Leads!N2:N101,MATCH(LARGE(Leads!U2:U101,2),Leads!U2:U101,0)),"$#,##0")&" in potential revenue.")) -> You have 4 Hot Leads. Contact these 2 first — they represent your highest revenue opportunity today: 1. Carlos Vega ($1,400) — Priority call/text Carlos Vega — high interest, $1,400 opportunity 2. Emily & Josh Turner ($950) — Priority call/text Emily & Josh Turner — high interest, $950 opportunity Together they represent $2,350 in potential revenue. | I13: Appointment Booked | J13: =COUNTIF(Leads!$I$2:$I$101,"Appointment Booked") -> 2
I14: Trial Completed | J14: =COUNTIF(Leads!$I$2:$I$101,"Trial Completed") -> 0
I15: Enrolled | J15: =COUNTIF(Leads!$I$2:$I$101,"Enrolled") -> 1
I16: Lost | J16: =COUNTIF(Leads!$I$2:$I$101,"Lost") -> 1
B19: 📋 FOLLOW-UPS DUE TODAY OR OVERDUE
B20: Name | C20: Stage | D20: Status | E20: Suggested Action
B21: =IF(COUNTIF(Leads!$V$2:$V$101,">0")<1,"",IFERROR(INDEX(Leads!$C$2:$C$101,MATCH(LARGE(Leads!$V$2:$V$101,1),Leads!$V$2:$V$101,0)),"")) -> Priya Nair | C21: =IF($B21="","",INDEX(Leads!$I$2:$I$101,MATCH(LARGE(Leads!$V$2:$V$101,1),Leads!$V$2:$V$101,0))) -> New Inquiry | D21: =IF($B21="","",INDEX(Leads!$Q$2:$Q$101,MATCH(LARGE(Leads!$V$2:$V$101,1),Leads!$V$2:$V$101,0))) -> Overdue | E21: =IF($B21="","",INDEX(Leads!$T$2:$T$101,MATCH(LARGE(Leads!$V$2:$V$101,1),Leads!$V$2:$V$101,0))) -> OVERDUE — contact Priya Nair today, follow-up was due 8/7
B22: =IF(COUNTIF(Leads!$V$2:$V$101,">0")<2,"",IFERROR(INDEX(Leads!$C$2:$C$101,MATCH(LARGE(Leads!$V$2:$V$101,2),Leads!$V$2:$V$101,0)),"")) -> Nicole Brooks | C22: =IF($B22="","",INDEX(Leads!$I$2:$I$101,MATCH(LARGE(Leads!$V$2:$V$101,2),Leads!$V$2:$V$101,0))) -> Contacted | D22: =IF($B22="","",INDEX(Leads!$Q$2:$Q$101,MATCH(LARGE(Leads!$V$2:$V$101,2),Leads!$V$2:$V$101,0))) -> Overdue | E22: =IF($B22="","",INDEX(Leads!$T$2:$T$101,MATCH(LARGE(Leads!$V$2:$V$101,2),Leads!$V$2:$V$101,0))) -> OVERDUE — contact Nicole Brooks today, follow-up was due 8/5
B23: =IF(COUNTIF(Leads!$V$2:$V$101,">0")<3,"",IFERROR(INDEX(Leads!$C$2:$C$101,MATCH(LARGE(Leads!$V$2:$V$101,3),Leads!$V$2:$V$101,0)),"")) -> Jessica Martinez | C23: =IF($B23="","",INDEX(Leads!$I$2:$I$101,MATCH(LARGE(Leads!$V$2:$V$101,3),Leads!$V$2:$V$101,0))) -> Qualified | D23: =IF($B23="","",INDEX(Leads!$Q$2:$Q$101,MATCH(LARGE(Leads!$V$2:$V$101,3),Leads!$V$2:$V$101,0))) -> Due Today | E23: =IF($B23="","",INDEX(Leads!$T$2:$T$101,MATCH(LARGE(Leads!$V$2:$V$101,3),Leads!$V$2:$V$101,0))) -> Priority call/text Jessica Martinez — high interest, $900 opportunity
B24: =IF(COUNTIF(Leads!$V$2:$V$101,">0")<4,"",IFERROR(INDEX(Leads!$C$2:$C$101,MATCH(LARGE(Leads!$V$2:$V$101,4),Leads!$V$2:$V$101,0)),"")) -> Michael Chen | C24: =IF($B24="","",INDEX(Leads!$I$2:$I$101,MATCH(LARGE(Leads!$V$2:$V$101,4),Leads!$V$2:$V$101,0))) -> Appointment Booked | D24: =IF($B24="","",INDEX(Leads!$Q$2:$Q$101,MATCH(LARGE(Leads!$V$2:$V$101,4),Leads!$V$2:$V$101,0))) -> Due Today | E24: =IF($B24="","",INDEX(Leads!$T$2:$T$101,MATCH(LARGE(Leads!$V$2:$V$101,4),Leads!$V$2:$V$101,0))) -> Priority call/text Michael Chen — high interest, $750 opportunity
B25: =IF(COUNTIF(Leads!$V$2:$V$101,">0")<5,"",IFERROR(INDEX(Leads!$C$2:$C$101,MATCH(LARGE(Leads!$V$2:$V$101,5),Leads!$V$2:$V$101,0)),"")) -> Carlos Vega | C25: =IF($B25="","",INDEX(Leads!$I$2:$I$101,MATCH(LARGE(Leads!$V$2:$V$101,5),Leads!$V$2:$V$101,0))) -> Qualified | D25: =IF($B25="","",INDEX(Leads!$Q$2:$Q$101,MATCH(LARGE(Leads!$V$2:$V$101,5),Leads!$V$2:$V$101,0))) -> Due Today | E25: =IF($B25="","",INDEX(Leads!$T$2:$T$101,MATCH(LARGE(Leads!$V$2:$V$101,5),Leads!$V$2:$V$101,0))) -> Priority call/text Carlos Vega — high interest, $1,400 opportunity
B26: =IF(COUNTIF(Leads!$V$2:$V$101,">0")<6,"",IFERROR(INDEX(Leads!$C$2:$C$101,MATCH(LARGE(Leads!$V$2:$V$101,6),Leads!$V$2:$V$101,0)),"")) | C26: =IF($B26="","",INDEX(Leads!$I$2:$I$101,MATCH(LARGE(Leads!$V$2:$V$101,6),Leads!$V$2:$V$101,0))) | D26: =IF($B26="","",INDEX(Leads!$Q$2:$Q$101,MATCH(LARGE(Leads!$V$2:$V$101,6),Leads!$V$2:$V$101,0))) | E26: =IF($B26="","",INDEX(Leads!$T$2:$T$101,MATCH(LARGE(Leads!$V$2:$V$101,6),Leads!$V$2:$V$101,0)))
B27: =IF(COUNTIF(Leads!$V$2:$V$101,">0")<7,"",IFERROR(INDEX(Leads!$C$2:$C$101,MATCH(LARGE(Leads!$V$2:$V$101,7),Leads!$V$2:$V$101,0)),"")) | C27: =IF($B27="","",INDEX(Leads!$I$2:$I$101,MATCH(LARGE(Leads!$V$2:$V$101,7),Leads!$V$2:$V$101,0))) | D27: =IF($B27="","",INDEX(Leads!$Q$2:$Q$101,MATCH(LARGE(Leads!$V$2:$V$101,7),Leads!$V$2:$V$101,0))) | E27: =IF($B27="","",INDEX(Leads!$T$2:$T$101,MATCH(LARGE(Leads!$V$2:$V$101,7),Leads!$V$2:$V$101,0)))
B28: =IF(COUNTIF(Leads!$V$2:$V$101,">0")<8,"",IFERROR(INDEX(Leads!$C$2:$C$101,MATCH(LARGE(Leads!$V$2:$V$101,8),Leads!$V$2:$V$101,0)),"")) | C28: =IF($B28="","",INDEX(Leads!$I$2:$I$101,MATCH(LARGE(Leads!$V$2:$V$101,8),Leads!$V$2:$V$101,0))) | D28: =IF($B28="","",INDEX(Leads!$Q$2:$Q$101,MATCH(LARGE(Leads!$V$2:$V$101,8),Leads!$V$2:$V$101,0))) | E28: =IF($B28="","",INDEX(Leads!$T$2:$T$101,MATCH(LARGE(Leads!$V$2:$V$101,8),Leads!$V$2:$V$101,0)))

Sheet Leads
A1: ID | G1: Goal / Notes | H1: Lead Source | I1: Pipeline Stage | J1: Last Contact | K1: Next Follow-Up | L1: Assigned Instructor | M1: Recommended Product | N1: Potential Revenue ($) | O1: Engagement (1-5) | P1: Days Since Inquiry | Q1: Follow-Up Status | R1: Lead Temperature | S1: Stage Weight | T1: AI Next Action | U1: Hot Rank Key | V1: FollowUp Rank Key
A2: 1 | B2: 46239 | C2: Jessica Martinez | D2: 480-555-0142 | E2: jessica.m@email.com | F2: Wedding Dance | G2: Wedding is Oct 17, wants 6 private lessons before then | H2: Instagram | I2: Qualified | J2: 46241 | K2: 46242 | L2: Brigette | M2: Wedding Package (Private Lessons) | N2: 900 | O2: 5 | P2: =IF(B2="","",TODAY()-B2) -> 3 | Q2: =IF(OR(K2="",I2="Enrolled",I2="Lost"),"--",IF(K2<TODAY(),"Overdue",IF(K2=TODAY(),"Due Today","Upcoming"))) -> Due Today | R2: =IF(C2="","",IF(OR(I2="Enrolled",I2="Lost"),"Closed",IF(OR(I2="Appointment Booked",I2="Trial Completed",O2>=5,AND(I2="Qualified",O2>=4)),"Hot",IF(OR(I2="Qualified",I2="Contacted",O2=3),"Warm","Cold")))) -> Hot | S2: =IF(I2="","",IFERROR(INDEX(Reference!$B$4:$B$10,MATCH(I2,Reference!$A$4:$A$10,0)),0)) -> 0.35 | T2: =IF(C2="","",IF(I2="Enrolled","Enrolled — welcome them and ask for a referral",IF(I2="Lost","Closed out — add to a win-back nurture sequence",IF(Q2="Overdue","OVERDUE — contact "&C2&" today, follow-up was due "&TEXT(K2,"m/d"),IF(R2="Hot","Priority call/text "&C2&" — high interest, "&TEXT(N2,"$#,##0")&" opportunity",IF(R2="Warm","Send "&C2&" info on the "&M2&" and confirm next step","Light-touch check-in with "&C2&" to re-engage")))))) -> Priority call/text Jessica Martinez — high interest, $900 opportunity | U2: =IF(R2="Hot",N2+ROW()/100000,-1) -> 900.00002 | V2: =IF(OR(Q2="Overdue",Q2="Due Today"),IF(Q2="Overdue",2000000,1000000)-ROW(),-1) -> 999998
A3: 2 | B3: 46238 | C3: Michael Chen | D3: 602-555-0198 | E3: mchen@email.com | F3: Private Lessons | G3: Wants weekly privates, flexible schedule, asked about pricing twice | H3: Website Form | I3: Appointment Booked | J3: 46240 | K3: 46242 | L3: Robert | M3: Private Lesson Package | N3: 750 | O3: 5 | P3: =IF(B3="","",TODAY()-B3) -> 4 | Q3: =IF(OR(K3="",I3="Enrolled",I3="Lost"),"--",IF(K3<TODAY(),"Overdue",IF(K3=TODAY(),"Due Today","Upcoming"))) -> Due Today | R3: =IF(C3="","",IF(OR(I3="Enrolled",I3="Lost"),"Closed",IF(OR(I3="Appointment Booked",I3="Trial Completed",O3>=5,AND(I3="Qualified",O3>=4)),"Hot",IF(OR(I3="Qualified",I3="Contacted",O3=3),"Warm","Cold")))) -> Hot | S3: =IF(I3="","",IFERROR(INDEX(Reference!$B$4:$B$10,MATCH(I3,Reference!$A$4:$A$10,0)),0)) -> 0.55 | T3: =IF(C3="","",IF(I3="Enrolled","Enrolled — welcome them and ask for a referral",IF(I3="Lost","Closed out — add to a win-back nurture sequence",IF(Q3="Overdue","OVERDUE — contact "&C3&" today, follow-up was due "&TEXT(K3,"m/d"),IF(R3="Hot","Priority call/text "&C3&" — high interest, "&TEXT(N3,"$#,##0")&" opportunity",IF(R3="Warm","Send "&C3&" info on the "&M3&" and confirm next step","Light-touch check-in with "&C3&" to re-engage")))))) -> Priority call/text Michael Chen — high interest, $750 opportunity | U3: =IF(R3="Hot",N3+ROW()/100000,-1) -> 750.00003 | V3: =IF(OR(Q3="Overdue",Q3="Due Today"),IF(Q3="Overdue",2000000,1000000)-ROW(),-1) -> 999997
A4: 3 | B4: 46237 | C4: Ashley Ramirez | D4: 623-555-0177 | E4: a.ramirez@email.com | F4: Beginner / Never Danced | G4: Never danced before, nervous, wants a friendly first class | H4: QR Code | I4: Contacted | J4: 46239 | K4: 46243 | L4: Unassigned | M4: Beginner Program | N4: 320 | O4: 3 | P4: =IF(B4="","",TODAY()-B4) -> 5 | Q4: =IF(OR(K4="",I4="Enrolled",I4="Lost"),"--",IF(K4<TODAY(),"Overdue",IF(K4=TODAY(),"Due Today","Upcoming"))) -> Upcoming | R4: =IF(C4="","",IF(OR(I4="Enrolled",I4="Lost"),"Closed",IF(OR(I4="Appointment Booked",I4="Trial Completed",O4>=5,AND(I4="Qualified",O4>=4)),"Hot",IF(OR(I4="Qualified",I4="Contacted",O4=3),"Warm","Cold")))) -> Warm | S4: =IF(I4="","",IFERROR(INDEX(Reference!$B$4:$B$10,MATCH(I4,Reference!$A$4:$A$10,0)),0)) -> 0.2 | T4: =IF(C4="","",IF(I4="Enrolled","Enrolled — welcome them and ask for a referral",IF(I4="Lost","Closed out — add to a win-back nurture sequence",IF(Q4="Overdue","OVERDUE — contact "&C4&" today, follow-up was due "&TEXT(K4,"m/d"),IF(R4="Hot","Priority call/text "&C4&" — high interest, "&TEXT(N4,"$#,##0")&" opportunity",IF(R4="Warm","Send "&C4&" info on the "&M4&" and confirm next step","Light-touch check-in with "&C4&" to re-engage")))))) -> Send Ashley Ramirez info on the Beginner Program and confirm next step | U4: =IF(R4="Hot",N4+ROW()/100000,-1) -> -1 | V4: =IF(OR(Q4="Overdue",Q4="Due Today"),IF(Q4="Overdue",2000000,1000000)-ROW(),-1) -> -1
A5: 4 | B5: 46236 | C5: Daniel Osei | D5: 480-555-0133 | E5: daniel.osei@email.com | F5: Social Dancing | G5: Wants to come to Friday socials, casual interest | H5: Facebook | I5: New Inquiry | J5: 46237 | K5: 46244 | L5: Unassigned | M5: Social/Practice Party Pass | N5: 120 | O5: 2 | P5: =IF(B5="","",TODAY()-B5) -> 6 | Q5: =IF(OR(K5="",I5="Enrolled",I5="Lost"),"--",IF(K5<TODAY(),"Overdue",IF(K5=TODAY(),"Due Today","Upcoming"))) -> Upcoming | R5: =IF(C5="","",IF(OR(I5="Enrolled",I5="Lost"),"Closed",IF(OR(I5="Appointment Booked",I5="Trial Completed",O5>=5,AND(I5="Qualified",O5>=4)),"Hot",IF(OR(I5="Qualified",I5="Contacted",O5=3),"Warm","Cold")))) -> Cold | S5: =IF(I5="","",IFERROR(INDEX(Reference!$B$4:$B$10,MATCH(I5,Reference!$A$4:$A$10,0)),0)) -> 0.1 | T5: =IF(C5="","",IF(I5="Enrolled","Enrolled — welcome them and ask for a referral",IF(I5="Lost","Closed out — add to a win-back nurture sequence",IF(Q5="Overdue","OVERDUE — contact "&C5&" today, follow-up was due "&TEXT(K5,"m/d"),IF(R5="Hot","Priority call/text "&C5&" — high interest, "&TEXT(N5,"$#,##0")&" opportunity",IF(R5="Warm","Send "&C5&" info on the "&M5&" and confirm next step","Light-touch check-in with "&C5&" to re-engage")))))) -> Light-touch check-in with Daniel Osei to re-engage | U5: =IF(R5="Hot",N5+ROW()/100000,-1) -> -1 | V5: =IF(OR(Q5="Overdue",Q5="Due Today"),IF(Q5="Overdue",2000000,1000000)-ROW(),-1) -> -1
A6: 5 | B6: 46235 | C6: Emily & Josh Turner | D6: 602-555-0111 | E6: emily.turner@email.com | F6: Wedding Dance | G6: Wedding in Dec, first dance to a specific song, very responsive | H6: Referral | I6: Appointment Booked | J6: 46242 | K6: 46243 | L6: Brigette | M6: Wedding Package (Private Lessons) | N6: 950 | O6: 5 | P6: =IF(B6="","",TODAY()-B6) -> 7 | Q6: =IF(OR(K6="",I6="Enrolled",I6="Lost"),"--",IF(K6<TODAY(),"Overdue",IF(K6=TODAY(),"Due Today","Upcoming"))) -> Upcoming | R6: =IF(C6="","",IF(OR(I6="Enrolled",I6="Lost"),"Closed",IF(OR(I6="Appointment Booked",I6="Trial Completed",O6>=5,AND(I6="Qualified",O6>=4)),"Hot",IF(OR(I6="Qualified",I6="Contacted",O6=3),"Warm","Cold")))) -> Hot | S6: =IF(I6="","",IFERROR(INDEX(Reference!$B$4:$B$10,MATCH(I6,Reference!$A$4:$A$10,0)),0)) -> 0.55 | T6: =IF(C6="","",IF(I6="Enrolled","Enrolled — welcome them and ask for a referral",IF(I6="Lost","Closed out — add to a win-back nurture sequence",IF(Q6="Overdue","OVERDUE — contact "&C6&" today, follow-up was due "&TEXT(K6,"m/d"),IF(R6="Hot","Priority call/text "&C6&" — high interest, "&TEXT(N6,"$#,##0")&" opportunity",IF(R6="Warm","Send "&C6&" info on the "&M6&" and confirm next step","Light-touch check-in with "&C6&" to re-engage")))))) -> Priority call/text Emily & Josh Turner — high interest, $950 opportunity | U6: =IF(R6="Hot",N6+ROW()/100000,-1) -> 950.00006 | V6: =IF(OR(Q6="Overdue",Q6="Due Today"),IF(Q6="Overdue",2000000,1000000)-ROW(),-1) -> -1
A7: 6 | B7: 46234 | C7: Priya Nair | D7: 480-555-0166 | E7: priya.nair@email.com | F7: Group Class | G7: Interested in beginner group series starting next month | H7: Instagram | I7: New Inquiry | J7: 46235 | K7: 46241 | L7: Unassigned | M7: Group Class Series | N7: 240 | O7: 2 | P7: =IF(B7="","",TODAY()-B7) -> 8 | Q7: =IF(OR(K7="",I7="Enrolled",I7="Lost"),"--",IF(K7<TODAY(),"Overdue",IF(K7=TODAY(),"Due Today","Upcoming"))) -> Overdue | R7: =IF(C7="","",IF(OR(I7="Enrolled",I7="Lost"),"Closed",IF(OR(I7="Appointment Booked",I7="Trial Completed",O7>=5,AND(I7="Qualified",O7>=4)),"Hot",IF(OR(I7="Qualified",I7="Contacted",O7=3),"Warm","Cold")))) -> Cold | S7: =IF(I7="","",IFERROR(INDEX(Reference!$B$4:$B$10,MATCH(I7,Reference!$A$4:$A$10,0)),0)) -> 0.1 | T7: =IF(C7="","",IF(I7="Enrolled","Enrolled — welcome them and ask for a referral",IF(I7="Lost","Closed out — add to a win-back nurture sequence",IF(Q7="Overdue","OVERDUE — contact "&C7&" today, follow-up was due "&TEXT(K7,"m/d"),IF(R7="Hot","Priority call/text "&C7&" — high interest, "&TEXT(N7,"$#,##0")&" opportunity",IF(R7="Warm","Send "&C7&" info on the "&M7&" and confirm next step","Light-touch check-in with "&C7&" to re-engage")))))) -> OVERDUE — contact Priya Nair today, follow-up was due 8/7 | U7: =IF(R7="Hot",N7+ROW()/100000,-1) -> -1 | V7: =IF(OR(Q7="Overdue",Q7="Due Today"),IF(Q7="Overdue",2000000,1000000)-ROW(),-1) -> 1999993
A8: 7 | B8: 46233 | C8: Carlos Vega | D8: 623-555-0155 | E8: carlos.vega@email.com | F8: Competitive / Team | G8: Former dancer, wants to join competitive team, very motivated | H8: Walk-In | I8: Qualified | J8: 46241 | K8: 46242 | L8: Robert | M8: Competitive Team Program | N8: 1400 | O8: 4 | P8: =IF(B8="","",TODAY()-B8) -> 9 | Q8: =IF(OR(K8="",I8="Enrolled",I8="Lost"),"--",IF(K8<TODAY(),"Overdue",IF(K8=TODAY(),"Due Today","Upcoming"))) -> Due Today | R8: =IF(C8="","",IF(OR(I8="Enrolled",I8="Lost"),"Closed",IF(OR(I8="Appointment Booked",I8="Trial Completed",O8>=5,AND(I8="Qualified",O8>=4)),"Hot",IF(OR(I8="Qualified",I8="Contacted",O8=3),"Warm","Cold")))) -> Hot | S8: =IF(I8="","",IFERROR(INDEX(Reference!$B$4:$B$10,MATCH(I8,Reference!$A$4:$A$10,0)),0)) -> 0.35 | T8: =IF(C8="","",IF(I8="Enrolled","Enrolled — welcome them and ask for a referral",IF(I8="Lost","Closed out — add to a win-back nurture sequence",IF(Q8="Overdue","OVERDUE — contact "&C8&" today, follow-up was due "&TEXT(K8,"m/d"),IF(R8="Hot","Priority call/text "&C8&" — high interest, "&TEXT(N8,"$#,##0")&" opportunity",IF(R8="Warm","Send "&C8&" info on the "&M8&" and confirm next step","Light-touch check-in with "&C8&" to re-engage")))))) -> Priority call/text Carlos Vega — high interest, $1,400 opportunity | U8: =IF(R8="Hot",N8+ROW()/100000,-1) -> 1400.0001 | V8: =IF(OR(Q8="Overdue",Q8="Due Today"),IF(Q8="Overdue",2000000,1000000)-ROW(),-1) -> 999992
A9: 8 | B9: 46232 | C9: Nicole Brooks | D9: 480-555-0121 | E9: nicole.b@email.com | F9: Beginner / Never Danced | G9: Asked about intro offer, hasn't responded to last text | H9: Google/Search | I9: Contacted | J9: 46232 | K9: 46239 | L9: Unassigned | M9: Beginner Program | N9: 300 | O9: 1 | P9: =IF(B9="","",TODAY()-B9) -> 10 | Q9: =IF(OR(K9="",I9="Enrolled",I9="Lost"),"--",IF(K9<TODAY(),"Overdue",IF(K9=TODAY(),"Due Today","Upcoming"))) -> Overdue | R9: =IF(C9="","",IF(OR(I9="Enrolled",I9="Lost"),"Closed",IF(OR(I9="Appointment Booked",I9="Trial Completed",O9>=5,AND(I9="Qualified",O9>=4)),"Hot",IF(OR(I9="Qualified",I9="Contacted",O9=3),"Warm","Cold")))) -> Warm | S9: =IF(I9="","",IFERROR(INDEX(Reference!$B$4:$B$10,MATCH(I9,Reference!$A$4:$A$10,0)),0)) -> 0.2 | T9: =IF(C9="","",IF(I9="Enrolled","Enrolled — welcome them and ask for a referral",IF(I9="Lost","Closed out — add to a win-back nurture sequence",IF(Q9="Overdue","OVERDUE — contact "&C9&" today, follow-up was due "&TEXT(K9,"m/d"),IF(R9="Hot","Priority call/text "&C9&" — high interest, "&TEXT(N9,"$#,##0")&" opportunity",IF(R9="Warm","Send "&C9&" info on the "&M9&" and confirm next step","Light-touch check-in with "&C9&" to re-engage")))))) -> OVERDUE — contact Nicole Brooks today, follow-up was due 8/5 | U9: =IF(R9="Hot",N9+ROW()/100000,-1) -> -1 | V9: =IF(OR(Q9="Overdue",Q9="Due Today"),IF(Q9="Overdue",2000000,1000000)-ROW(),-1) -> 1999991
A10: 9 | B10: 46231 | C10: Marcus Johnson | D10: 602-555-0144 | E10: marcus.j@email.com | F10: Private Lessons | G10: Enrolled after trial lesson, loves West Coast Swing | H10: Referral | I10: Enrolled | J10: 46228 | K10: 46272 | L10: Robert | M10: Private Lesson Package | N10: 1200 | O10: 5 | P10: =IF(B10="","",TODAY()-B10) -> 11 | Q10: =IF(OR(K10="",I10="Enrolled",I10="Lost"),"--",IF(K10<TODAY(),"Overdue",IF(K10=TODAY(),"Due Today","Upcoming"))) -> -- | R10: =IF(C10="","",IF(OR(I10="Enrolled",I10="Lost"),"Closed",IF(OR(I10="Appointment Booked",I10="Trial Completed",O10>=5,AND(I10="Qualified",O10>=4)),"Hot",IF(OR(I10="Qualified",I10="Contacted",O10=3),"Warm","Cold")))) -> Closed | S10: =IF(I10="","",IFERROR(INDEX(Reference!$B$4:$B$10,MATCH(I10,Reference!$A$4:$A$10,0)),0)) -> 1 | T10: =IF(C10="","",IF(I10="Enrolled","Enrolled — welcome them and ask for a referral",IF(I10="Lost","Closed out — add to a win-back nurture sequence",IF(Q10="Overdue","OVERDUE — contact "&C10&" today, follow-up was due "&TEXT(K10,"m/d"),IF(R10="Hot","Priority call/text "&C10&" — high interest, "&TEXT(N10,"$#,##0")&" opportunity",IF(R10="Warm","Send "&C10&" info on the "&M10&" and confirm next step","Light-touch check-in with "&C10&" to re-engage")))))) -> Enrolled — welcome them and ask for a referral | U10: =IF(R10="Hot",N10+ROW()/100000,-1) -> -1 | V10: =IF(OR(Q10="Overdue",Q10="Due Today"),IF(Q10="Overdue",2000000,1000000)-ROW(),-1) -> -1
A11: 10 | B11: 46230 | C11: Grace Kim | D11: 623-555-0188 | E11: grace.kim@email.com | F11: Workshop / Event | G11: Signed up then went quiet, hasn't responded in 3 weeks | H11: Event | I11: Lost | J11: 46217 | K11: 46222 | L11: Unassigned | M11: Workshop Ticket | N11: 75 | O11: 1 | P11: =IF(B11="","",TODAY()-B11) -> 12 | Q11: =IF(OR(K11="",I11="Enrolled",I11="Lost"),"--",IF(K11<TODAY(),"Overdue",IF(K11=TODAY(),"Due Today","Upcoming"))) -> -- | R11: =IF(C11="","",IF(OR(I11="Enrolled",I11="Lost"),"Closed",IF(OR(I11="Appointment Booked",I11="Trial Completed",O11>=5,AND(I11="Qualified",O11>=4)),"Hot",IF(OR(I11="Qualified",I11="Contacted",O11=3),"Warm","Cold")))) -> Closed | S11: =IF(I11="","",IFERROR(INDEX(Reference!$B$4:$B$10,MATCH(I11,Reference!$A$4:$A$10,0)),0)) -> 0 | T11: =IF(C11="","",IF(I11="Enrolled","Enrolled — welcome them and ask for a referral",IF(I11="Lost","Closed out — add to a win-back nurture sequence",IF(Q11="Overdue","OVERDUE — contact "&C11&" today, follow-up was due "&TEXT(K11,"m/d"),IF(R11="Hot","Priority call/text "&C11&" — high interest, "&TEXT(N11,"$#,##0")&" opportunity",IF(R11="Warm","Send "&C11&" info on the "&M11&" and confirm next step","Light-touch check-in with "&C11&" to re-engage")))))) -> Closed out — add to a win-back nurture sequence | U11: =IF(R11="Hot",N11+ROW()/100000,-1) -> -1 | V11: =IF(OR(Q11="Overdue",Q11="Due Today"),IF(Q11="Overdue",2000000,1000000)-ROW(),-1) -> -1
P12: =IF(B12="","",TODAY()-B12) | Q12: =IF(OR(K12="",I12="Enrolled",I12="Lost"),"--",IF(K12<TODAY(),"Overdue",IF(K12=TODAY(),"Due Today","Upcoming"))) -> -- | R12: =IF(C12="","",IF(OR(I12="Enrolled",I12="Lost"),"Closed",IF(OR(I12="Appointment Booked",I12="Trial Completed",O12>=5,AND(I12="Qualified",O12>=4)),"Hot",IF(OR(I12="Qualified",I12="Contacted",O12=3),"Warm","Cold")))) | S12: =IF(I12="","",IFERROR(INDEX(Reference!$B$4:$B$10,MATCH(I12,Reference!$A$4:$A$10,0)),0)) | T12: =IF(C12="","",IF(I12="Enrolled","Enrolled — welcome them and ask for a referral",IF(I12="Lost","Closed out — add to a win-back nurture sequence",IF(Q12="Overdue","OVERDUE — contact "&C12&" today, follow-up was due "&TEXT(K12,"m/d"),IF(R12="Hot","Priority call/text "&C12&" — high interest, "&TEXT(N12,"$#,##0")&" opportunity",IF(R12="Warm","Send "&C12&" info on the "&M12&" and confirm next step","Light-touch check-in with "&C12&" to re-engage")))))) | U12: =IF(R12="Hot",N12+ROW()/100000,-1) -> -1 | V12: =IF(OR(Q12="Overdue",Q12="Due Today"),IF(Q12="Overdue",2000000,1000000)-ROW(),-1) -> -1
P13: =IF(B13="","",TODAY()-B13) | Q13: =IF(OR(K13="",I13="Enrolled",I13="Lost"),"--",IF(K13<TODAY(),"Overdue",IF(K13=TODAY(),"Due Today","Upcoming"))) -> -- | R13: =IF(C13="","",IF(OR(I13="Enrolled",I13="Lost"),"Closed",IF(OR(I13="Appointment Booked",I13="Trial Completed",O13>=5,AND(I13="Qualified",O13>=4)),"Hot",IF(OR(I13="Qualified",I13="Contacted",O13=3),"Warm","Cold")))) | S13: =IF(I13="","",IFERROR(INDEX(Reference!$B$4:$B$10,MATCH(I13,Reference!$A$4:$A$10,0)),0)) | T13: =IF(C13="","",IF(I13="Enrolled","Enrolled — welcome them and ask for a referral",IF(I13="Lost","Closed out — add to a win-back nurture sequence",IF(Q13="Overdue","OVERDUE — contact "&C13&" today, follow-up was due "&TEXT(K13,"m/d"),IF(R13="Hot","Priority call/text "&C13&" — high interest, "&TEXT(N13,"$#,##0")&" opportunity",IF(R13="Warm","Send "&C13&" info on the "&M13&" and confirm next step","Light-touch check-in with "&C13&" to re-engage")))))) | U13: =IF(R13="Hot",N13+ROW()/100000,-1) -> -1 | V13: =IF(OR(Q13="Overdue",Q13="Due Today"),IF(Q13="Overdue",2000000,1000000)-ROW(),-1) -> -1
P14: =IF(B14="","",TODAY()-B14) | Q14: =IF(OR(K14="",I14="Enrolled",I14="Lost"),"--",IF(K14<TODAY(),"Overdue",IF(K14=TODAY(),"Due Today","Upcoming"))) -> -- | R14: =IF(C14="","",IF(OR(I14="Enrolled",I14="Lost"),"Closed",IF(OR(I14="Appointment Booked",I14="Trial Completed",O14>=5,AND(I14="Qualified",O14>=4)),"Hot",IF(OR(I14="Qualified",I14="Contacted",O14=3),"Warm","Cold")))) | S14: =IF(I14="","",IFERROR(INDEX(Reference!$B$4:$B$10,MATCH(I14,Reference!$A$4:$A$10,0)),0)) | T14: =IF(C14="","",IF(I14="Enrolled","Enrolled — welcome them and ask for a referral",IF(I14="Lost","Closed out — add to a win-back nurture sequence",IF(Q14="Overdue","OVERDUE — contact "&C14&" today, follow-up was due "&TEXT(K14,"m/d"),IF(R14="Hot","Priority call/text "&C14&" — high interest, "&TEXT(N14,"$#,##0")&" opportunity",IF(R14="Warm","Send "&C14&" info on the "&M14&" and confirm next step","Light-touch check-in with "&C14&" to re-engage")))))) | U14: =IF(R14="Hot",N14+ROW()/100000,-1) -> -1 | V14: =IF(OR(Q14="Overdue",Q14="Due Today"),IF(Q14="Overdue",2000000,1000000)-ROW(),-1) -> -1
P15: =IF(B15="","",TODAY()-B15) | Q15: =IF(OR(K15="",I15="Enrolled",I15="Lost"),"--",IF(K15<TODAY(),"Overdue",IF(K15=TODAY(),"Due Today","Upcoming"))) -> -- | R15: =IF(C15="","",IF(OR(I15="Enrolled",I15="Lost"),"Closed",IF(OR(I15="Appointment Booked",I15="Trial Completed",O15>=5,AND(I15="Qualified",O15>=4)),"Hot",IF(OR(I15="Qualified",I15="Contacted",O15=3),"Warm","Cold")))) | S15: =IF(I15="","",IFERROR(INDEX(Reference!$B$4:$B$10,MATCH(I15,Reference!$A$4:$A$10,0)),0)) | T15: =IF(C15="","",IF(I15="Enrolled","Enrolled — welcome them and ask for a referral",IF(I15="Lost","Closed out — add to a win-back nurture sequence",IF(Q15="Overdue","OVERDUE — contact "&C15&" today, follow-up was due "&TEXT(K15,"m/d"),IF(R15="Hot","Priority call/text "&C15&" — high interest, "&TEXT(N15,"$#,##0")&" opportunity",IF(R15="Warm","Send "&C15&" info on the "&M15&" and confirm next step","Light-touch check-in with "&C15&" to re-engage")))))) | U15: =IF(R15="Hot",N15+ROW()/100000,-1) -> -1 | V15: =IF(OR(Q15="Overdue",Q15="Due Today"),IF(Q15="Overdue",2000000,1000000)-ROW(),-1) -> -1
P16: =IF(B16="","",TODAY()-B16) | Q16: =IF(OR(K16="",I16="Enrolled",I16="Lost"),"--",IF(K16<TODAY(),"Overdue",IF(K16=TODAY(),"Due Today","Upcoming"))) -> -- | R16: =IF(C16="","",IF(OR(I16="Enrolled",I16="Lost"),"Closed",IF(OR(I16="Appointment Booked",I16="Trial Completed",O16>=5,AND(I16="Qualified",O16>=4)),"Hot",IF(OR(I16="Qualified",I16="Contacted",O16=3),"Warm","Cold")))) | S16: =IF(I16="","",IFERROR(INDEX(Reference!$B$4:$B$10,MATCH(I16,Reference!$A$4:$A$10,0)),0)) | T16: =IF(C16="","",IF(I16="Enrolled","Enrolled — welcome them and ask for a referral",IF(I16="Lost","Closed out — add to a win-back nurture sequence",IF(Q16="Overdue","OVERDUE — contact "&C16&" today, follow-up was due "&TEXT(K16,"m/d"),IF(R16="Hot","Priority call/text "&C16&" — high interest, "&TEXT(N16,"$#,##0")&" opportunity",IF(R16="Warm","Send "&C16&" info on the "&M16&" and confirm next step","Light-touch check-in with "&C16&" to re-engage")))))) | U16: =IF(R16="Hot",N16+ROW()/100000,-1) -> -1 | V16: =IF(OR(Q16="Overdue",Q16="Due Today"),IF(Q16="Overdue",2000000,1000000)-ROW(),-1) -> -1
P17: =IF(B17="","",TODAY()-B17) | Q17: =IF(OR(K17="",I17="Enrolled",I17="Lost"),"--",IF(K17<TODAY(),"Overdue",IF(K17=TODAY(),"Due Today","Upcoming"))) -> -- | R17: =IF(C17="","",IF(OR(I17="Enrolled",I17="Lost"),"Closed",IF(OR(I17="Appointment Booked",I17="Trial Completed",O17>=5,AND(I17="Qualified",O17>=4)),"Hot",IF(OR(I17="Qualified",I17="Contacted",O17=3),"Warm","Cold")))) | S17: =IF(I17="","",IFERROR(INDEX(Reference!$B$4:$B$10,MATCH(I17,Reference!$A$4:$A$10,0)),0)) | T17: =IF(C17="","",IF(I17="Enrolled","Enrolled — welcome them and ask for a referral",IF(I17="Lost","Closed out — add to a win-back nurture sequence",IF(Q17="Overdue","OVERDUE — contact "&C17&" today, follow-up was due "&TEXT(K17,"m/d"),IF(R17="Hot","Priority call/text "&C17&" — high interest, "&TEXT(N17,"$#,##0")&" opportunity",IF(R17="Warm","Send "&C17&" info on the "&M17&" and confirm next step","Light-touch check-in with "&C17&" to re-engage")))))) | U17: =IF(R17="Hot",N17+ROW()/100000,-1) -> -1 | V17: =IF(OR(Q17="Overdue",Q17="Due Today"),IF(Q17="Overdue",2000000,1000000)-ROW(),-1) -> -1
P18: =IF(B18="","",TODAY()-B18) | Q18: =IF(OR(K18="",I18="Enrolled",I18="Lost"),"--",IF(K18<TODAY(),"Overdue",IF(K18=TODAY(),"Due Today","Upcoming"))) -> -- | R18: =IF(C18="","",IF(OR(I18="Enrolled",I18="Lost"),"Closed",IF(OR(I18="Appointment Booked",I18="Trial Completed",O18>=5,AND(I18="Qualified",O18>=4)),"Hot",IF(OR(I18="Qualified",I18="Contacted",O18=3),"Warm","Cold")))) | S18: =IF(I18="","",IFERROR(INDEX(Reference!$B$4:$B$10,MATCH(I18,Reference!$A$4:$A$10,0)),0)) | T18: =IF(C18="","",IF(I18="Enrolled","Enrolled — welcome them and ask for a referral",IF(I18="Lost","Closed out — add to a win-back nurture sequence",IF(Q18="Overdue","OVERDUE — contact "&C18&" today, follow-up was due "&TEXT(K18,"m/d"),IF(R18="Hot","Priority call/text "&C18&" — high interest, "&TEXT(N18,"$#,##0")&" opportunity",IF(R18="Warm","Send "&C18&" info on the "&M18&" and confirm next step","Light-touch check-in with "&C18&" to re-engage")))))) | U18: =IF(R18="Hot",N18+ROW()/100000,-1) -> -1 | V18: =IF(OR(Q18="Overdue",Q18="Due Today"),IF(Q18="Overdue",2000000,1000000)-ROW(),-1) -> -1
P19: =IF(B19="","",TODAY()-B19) | Q19: =IF(OR(K19="",I19="Enrolled",I19="Lost"),"--",IF(K19<TODAY(),"Overdue",IF(K19=TODAY(),"Due Today","Upcoming"))) -> -- | R19: =IF(C19="","",IF(OR(I19="Enrolled",I19="Lost"),"Closed",IF(OR(I19="Appointment Booked",I19="Trial Completed",O19>=5,AND(I19="Qualified",O19>=4)),"Hot",IF(OR(I19="Qualified",I19="Contacted",O19=3),"Warm","Cold")))) | S19: =IF(I19="","",IFERROR(INDEX(Reference!$B$4:$B$10,MATCH(I19,Reference!$A$4:$A$10,0)),0)) | T19: =IF(C19="","",IF(I19="Enrolled","Enrolled — welcome them and ask for a referral",IF(I19="Lost","Closed out — add to a win-back nurture sequence",IF(Q19="Overdue","OVERDUE — contact "&C19&" today, follow-up was due "&TEXT(K19,"m/d"),IF(R19="Hot","Priority call/text "&C19&" — high interest, "&TEXT(N19,"$#,##0")&" opportunity",IF(R19="Warm","Send "&C19&" info on the "&M19&" and confirm next step","Light-touch check-in with "&C19&" to re-engage")))))) | U19: =IF(R19="Hot",N19+ROW()/100000,-1) -> -1 | V19: =IF(OR(Q19="Overdue",Q19="Due Today"),IF(Q19="Overdue",2000000,1000000)-ROW(),-1) -> -1
P20: =IF(B20="","",TODAY()-B20) | Q20: =IF(OR(K20="",I20="Enrolled",I20="Lost"),"--",IF(K20<TODAY(),"Overdue",IF(K20=TODAY(),"Due Today","Upcoming"))) -> -- | R20: =IF(C20="","",IF(OR(I20="Enrolled",I20="Lost"),"Closed",IF(OR(I20="Appointment Booked",I20="Trial Completed",O20>=5,AND(I20="Qualified",O20>=4)),"Hot",IF(OR(I20="Qualified",I20="Contacted",O20=3),"Warm","Cold")))) | S20: =IF(I20="","",IFERROR(INDEX(Reference!$B$4:$B$10,MATCH(I20,Reference!$A$4:$A$10,0)),0)) | T20: =IF(C20="","",IF(I20="Enrolled","Enrolled — welcome them and ask for a referral",IF(I20="Lost","Closed out — add to a win-back nurture sequence",IF(Q20="Overdue","OVERDUE — contact "&C20&" today, follow-up was due "&TEXT(K20,"m/d"),IF(R20="Hot","Priority call/text "&C20&" — high interest, "&TEXT(N20,"$#,##0")&" opportunity",IF(R20="Warm","Send "&C20&" info on the "&M20&" and confirm next step","Light-touch check-in with "&C20&" to re-engage")))))) | U20: =IF(R20="Hot",N20+ROW()/100000,-1) -> -1 | V20: =IF(OR(Q20="Overdue",Q20="Due Today"),IF(Q20="Overdue",2000000,1000000)-ROW(),-1) -> -1
P21: =IF(B21="","",TODAY()-B21) | Q21: =IF(OR(K21="",I21="Enrolled",I21="Lost"),"--",IF(K21<TODAY(),"Overdue",IF(K21=TODAY(),"Due Today","Upcoming"))) -> -- | R21: =IF(C21="","",IF(OR(I21="Enrolled",I21="Lost"),"Closed",IF(OR(I21="Appointment Booked",I21="Trial Completed",O21>=5,AND(I21="Qualified",O21>=4)),"Hot",IF(OR(I21="Qualified",I21="Contacted",O21=3),"Warm","Cold")))) | S21: =IF(I21="","",IFERROR(INDEX(Reference!$B$4:$B$10,MATCH(I21,Reference!$A$4:$A$10,0)),0)) | T21: =IF(C21="","",IF(I21="Enrolled","Enrolled — welcome them and ask for a referral",IF(I21="Lost","Closed out — add to a win-back nurture sequence",IF(Q21="Overdue","OVERDUE — contact "&C21&" today, follow-up was due "&TEXT(K21,"m/d"),IF(R21="Hot","Priority call/text "&C21&" — high interest, "&TEXT(N21,"$#,##0")&" opportunity",IF(R21="Warm","Send "&C21&" info on the "&M21&" and confirm next step","Light-touch check-in with "&C21&" to re-engage")))))) | U21: =IF(R21="Hot",N21+ROW()/100000,-1) -> -1 | V21: =IF(OR(Q21="Overdue",Q21="Due Today"),IF(Q21="Overdue",2000000,1000000)-ROW(),-1) -> -1
P22: =IF(B22="","",TODAY()-B22) | Q22: =IF(OR(K22="",I22="Enrolled",I22="Lost"),"--",IF(K22<TODAY(),"Overdue",IF(K22=TODAY(),"Due Today","Upcoming"))) -> -- | R22: =IF(C22="","",IF(OR(I22="Enrolled",I22="Lost"),"Closed",IF(OR(I22="Appointment Booked",I22="Trial Completed",O22>=5,AND(I22="Qualified",O22>=4)),"Hot",IF(OR(I22="Qualified",I22="Contacted",O22=3),"Warm","Cold")))) | S22: =IF(I22="","",IFERROR(INDEX(Reference!$B$4:$B$10,MATCH(I22,Reference!$A$4:$A$10,0)),0)) | T22: =IF(C22="","",IF(I22="Enrolled","Enrolled — welcome them and ask for a referral",IF(I22="Lost","Closed out — add to a win-back nurture sequence",IF(Q22="Overdue","OVERDUE — contact "&C22&" today, follow-up was due "&TEXT(K22,"m/d"),IF(R22="Hot","Priority call/text "&C22&" — high interest, "&TEXT(N22,"$#,##0")&" opportunity",IF(R22="Warm","Send "&C22&" info on the "&M22&" and confirm next step","Light-touch check-in with "&C22&" to re-engage")))))) | U22: =IF(R22="Hot",N22+ROW()/100000,-1) -> -1 | V22: =IF(OR(Q22="Overdue",Q22="Due Today"),IF(Q22="Overdue",2000000,1000000)-ROW(),-1) -> -1
P23: =IF(B23="","",TODAY()-B23) | Q23: =IF(OR(K23="",I23="Enrolled",I23="Lost"),"--",IF(K23<TODAY(),"Overdue",IF(K23=TODAY(),"Due Today","Upcoming"))) -> -- | R23: =IF(C23="","",IF(OR(I23="Enrolled",I23="Lost"),"Closed",IF(OR(I23="Appointment Booked",I23="Trial Completed",O23>=5,AND(I23="Qualified",O23>=4)),"Hot",IF(OR(I23="Qualified",I23="Contacted",O23=3),"Warm","Cold")))) | S23: =IF(I23="","",IFERROR(INDEX(Reference!$B$4:$B$10,MATCH(I23,Reference!$A$4:$A$10,0)),0)) | T23: =IF(C23="","",IF(I23="Enrolled","Enrolled — welcome them and ask for a referral",IF(I23="Lost","Closed out — add to a win-back nurture sequence",IF(Q23="Overdue","OVERDUE — contact "&C23&" today, follow-up was due "&TEXT(K23,"m/d"),IF(R23="Hot","Priority call/text "&C23&" — high interest, "&TEXT(N23,"$#,##0")&" opportunity",IF(R23="Warm","Send "&C23&" info on the "&M23&" and confirm next step","Light-touch check-in with "&C23&" to re-engage")))))) | U23: =IF(R23="Hot",N23+ROW()/100000,-1) -> -1 | V23: =IF(OR(Q23="Overdue",Q23="Due Today"),IF(Q23="Overdue",2000000,1000000)-ROW(),-1) -> -1
... P101: =IF(B101="","",TODAY()-B101) | Q101: =IF(OR(K101="",I101="Enrolled",I101="Lost"),"--",IF(K101<TODAY(),"Overdue",IF(K101=TODAY(),"Due Today","Upcoming"))) -> -- | R101: =IF(C101="","",IF(OR(I101="Enrolled",I101="Lost"),"Closed",IF(OR(I101="Appointment Booked",I101="Trial Completed",O101>=5,AND(I101="Qualified",O101>=4)),"Hot",IF(OR(I101="Qualified",I101="Contacted",O101=3),"Warm","Cold")))) | S101: =IF(I101="","",IFERROR(INDEX(Reference!$B$4:$B$10,MATCH(I101,Reference!$A$4:$A$10,0)),0)) | T101: =IF(C101="","",IF(I101="Enrolled","Enrolled — welcome them and ask for a referral",IF(I101="Lost","Closed out — add to a win-back nurture sequence",IF(Q101="Overdue","OVERDUE — contact "&C101&" today, follow-up was due "&TEXT(K101,"m/d"),IF(R101="Hot","Priority call/text "&C101&" — high interest, "&TEXT(N101,"$#,##0")&" opportunity",IF(R101="Warm","Send "&C101&" info on the "&M101&" and confirm next step","Light-touch check-in with "&C101&" to re-engage")))))) | U101: =IF(R101="Hot",N101+ROW()/100000,-1) -> -1 | V101: =IF(OR(Q101="Overdue",Q101="Due Today"),IF(Q101="Overdue",2000000,1000000)-ROW(),-1) -> -1

Sheet Reference
A1: Reference Lists & Settings (edit to customize your business)
A3: Pipeline Stage | B3: Probability Weight | D3: Lead Source | F3: Dance Interest | G3: Suggested Product | I3: Assigned Instructor | K3: Engagement Score Guide
A4: New Inquiry | B4: 0.1 | D4: Instagram | F4: Wedding Dance | G4: Wedding Package (Private Lessons) | I4: Robert | K4: Score | L4: Meaning
A5: Contacted | B5: 0.2 | D5: Facebook | F5: Beginner / Never Danced | G5: Beginner Program | I5: Brigette | K5: 5 | L5: Very excited — fast replies, asking about price/dates
A6: Qualified | B6: 0.35 | D6: Website Form | F6: Private Lessons | G6: Private Lesson Package | I6: Unassigned | K6: 4 | L6: Interested — replies same day, asks real questions
A7: Appointment Booked | B7: 0.55 | D7: QR Code | F7: Group Class | G7: Group Class Series | K7: 3 | L7: Some interest — replies, but slow or noncommittal
A8: Trial Completed | B8: 0.75 | D8: Referral | F8: Social Dancing | G8: Social/Practice Party Pass | K8: 2 | L8: Lukewarm — one-word replies or long gaps
A9: Enrolled | B9: 1 | D9: Walk-In | F9: Competitive / Team | G9: Competitive Team Program | K9: 1 | L9: Cold — hasn't responded in a while
A10: Lost | B10: 0 | D10: Phone Call | F10: Kids Program | G10: Kids Beginner Program
D11: Google/Search | F11: Workshop / Event | G11: Workshop Ticket
D12: Event
D13: Other
A20: Lead Temperature Key (auto-calculated on the Leads tab)
A21: Hot | B21: Appointment booked, trial completed, or high engagement/qualified — contact today
A22: Warm | B22: Qualified, contacted, or moderate engagement — nurture with info and next steps
A23: Cold | B23: Low engagement, early stage — light-touch check-in
A24: Closed | B24: Already enrolled or marked lost
